{"chunk_definitions":[{"row":297,"row_count":1,"visible":true,"expansion_state":0,"options":{"engine":"r","label":"setup","include":false},"document_id":"C7E2FF9C","chunk_id":"csetup_chunk","chunk_label":"setup"},{"row":897,"row_count":1,"visible":true,"expansion_state":0,"options":{"engine":"r","label":"unnamed-chunk-328"},"document_id":"C7E2FF9C","chunk_id":"ci9x64zt0cq55","chunk_label":"unnamed-chunk-21"},{"row":929,"row_count":1,"visible":true,"expansion_state":0,"options":{"engine":"r","label":"plotly-food-dist-range"},"document_id":"C7E2FF9C","chunk_id":"ca0j02weil4fd","chunk_label":"plotly-food-dist-range"},{"row":955,"row_count":1,"visible":true,"expansion_state":0,"options":{"engine":"r","label":"unnamed-chunk-231"},"document_id":"C7E2FF9C","chunk_id":"co46m6effjxzu","chunk_label":"unnamed-chunk-22"},{"row":1015,"row_count":1,"visible":true,"expansion_state":0,"options":{"engine":"r","label":"unnamed-chunk-301"},"document_id":"C7E2FF9C","chunk_id":"c1jd6fcfk4hk9","chunk_label":"unnamed-chunk-24"},{"row":1104,"row_count":1,"visible":true,"expansion_state":0,"options":{"engine":"r","label":"unnamed-chunk-297"},"document_id":"C7E2FF9C","chunk_id":"cc45t7ndasnqi","chunk_label":"unnamed-chunk-28"}],"doc_write_time":1651600777,"working_dir":null,"default_chunk_options":{}}